sucks/__init__.py
sucks/cli.py
py_sucks-0.9.11.dist-info/LICENSE.txt
py_sucks-0.9.11.dist-info/METADATA
py_sucks-0.9.11.dist-info/WHEEL
py_sucks-0.9.11.dist-info/entry_points.txt
py_sucks-0.9.11.dist-info/top_level.txt
py_sucks-0.9.11.dist-info/RECORD
