Metadata-Version: 2.1
Name: py-sucks
Version: 0.9.11
Summary: a library for controlling certain robot vacuums
Home-page: https://github.com/mib1185/py-sucks
Author: William Pietri
Author-email: sucks-users@googlegroups.com
License: GPL-3.0
Keywords: home automation vacuum robot
Platform: UNKNOWN
Classifier: Development Status :: 4 - Beta
Classifier: Intended Audience :: Developers
Classifier: Topic :: Software Development :: Libraries
Classifier: Topic :: Home Automation
Classifier: License :: OSI Approved :: GNU General Public License v3 (GPLv3)
Classifier: Programming Language :: Python :: 3.9
Classifier: Programming Language :: Python :: 3.10
Classifier: Programming Language :: Python :: 3.11
Classifier: Programming Language :: Python :: 3.12
Provides-Extra: cli
Provides-Extra: dev
License-File: LICENSE.txt
